sashlab_stress/Participant.py
sashlab_stress/RoundInfo.py
sashlab_stress/__init__.py
sashlab_stress/__main__.py
sashlab_stress/attention.py
sashlab_stress/clear_prompt.py
sashlab_stress/dependencies.py
sashlab_stress/difficulty_manager.py
sashlab_stress/log_rounds.py
sashlab_stress/make_number.py
sashlab_stress/mental_subtraction.py
sashlab_stress/neg_neu_speech_task.py
sashlab_stress/session_setup.py
sashlab_stress/threaded_trial.py
sashlab_stress/trial.py
sashlab_stress-0.1.5.dist-info/METADATA
sashlab_stress-0.1.5.dist-info/WHEEL
sashlab_stress-0.1.5.dist-info/entry_points.txt
sashlab_stress-0.1.5.dist-info/RECORD
